README
setup.py
slowpoke/__init__.py
slowpoke/admin.py
slowpoke/decorator.py
slowpoke/models.py
slowpoke/router.py
slowpoke/runner.py
slowpoke/tests.py
slowpoke/views.py
slowpoke.egg-info/PKG-INFO
slowpoke.egg-info/SOURCES.txt
slowpoke.egg-info/dependency_links.txt
slowpoke.egg-info/top_level.txt